lhf-2.0.1.dist-info/RECORD
lhf-2.0.1.dist-info/top_level.txt
lhf-2.0.1.dist-info/METADATA
lhf-2.0.1.dist-info/WHEEL
pyLHF/__init__.py
pyLHF/__main__.py
pyLHF/pyLHF.py
lhf.libs/libmpfr-b7fafdf8.so.4.1.6
lhf.libs/libgmp-452f15e0.so.10.3.2
lhf.libs/libopen-pal-d1f167ef.so.40.30.1
lhf.libs/libreadInput-09604ee0.so
lhf.libs/libstreamingKmeans-1d5a99ac.so
lhf.libs/libhwloc-a765a097.so.15.2.0
lhf.libs/libmpi-2fa556dc.so.40.30.1
lhf.libs/libevent_core-2-e6cf51bb.1.so.6.0.2
lhf.libs/libkMeansPlusPlus-6a0e4583.so
lhf.libs/libgmpxx-6bc3ea01.so.4.5.2
lhf.libs/libstreamingUtils-33aec4bf.so
lhf.libs/libwriteOutput-6d79e888.so
lhf.libs/libcrypto-d9af65bd.so.1.1.1k
lhf.libs/libutils-fe381086.so
lhf.libs/libqhull_r-c601f68f.so.8.1-alpha3
lhf.libs/libmpi_cxx-c0da7930.so.40.30.0
lhf.libs/libcluster-6eab6735.so
lhf.libs/libdenStream-7f09c880.so
lhf.libs/libkdTree-17ab0886.so
lhf.libs/libdbscan-7d5374b7.so
lhf.libs/libopen-orted-mpir-06a2f0b2.so
lhf.libs/libopen-rte-1aa20eaf.so.40.30.1
lhf.libs/libpreprocessor-73ae98ae.so
lhf.libs/libevent_pthreads-2-9991b589.1.so.6.0.2
lhf.libs/libgomp-2c51bfab.so.1.0.0
lhf.libs/libargParser-e71dc2de.so
lhf/utilities.py
lhf/triangulation.py
lhf/__init__.py
lhf/libLHFlib.so
lhf/curves.py
lhf/DataGeneration/embeddings.py
lhf/DataGeneration/projectivePlane.py
lhf/DataGeneration/dataGen.py
lhf/DataGeneration/objGen.py
lhf/DataGeneration/torus.py
lhf/DataGeneration/__init__.py
lhf/DataGeneration/dSphere.py
lhf/OutputAnalysis/persistenceDiagrams.py
lhf/OutputAnalysis/piFilters.py
lhf/OutputAnalysis/__init__.py
lhf/OutputAnalysis/barcodeDiagrams.py
lhf/OutputAnalysis/bettiCurve.py
lhf/OutputAnalysis/heatmap.py
lhf/OutputAnalysis/filtrationImage.py
