Metadata-Version: 2.1
Name: lhf
Version: 2.0.1
Summary: Light Weight Homology Framework
Home-page: UNKNOWN
License: UNKNOWN
Project-URL: LHF (cpp) on GitHub, https://github.com/wilseypa/lhf
Project-URL: pyLHF on PyPi, https://pypi.org/project/lhf
Platform: UNKNOWN
Classifier: Programming Language :: Python :: 3
Classifier: License :: OSI Approved :: MIT License
Classifier: Operating System :: OS Independent
Requires-Dist: numpy
Requires-Dist: scipy
Requires-Dist: scikit-learn
Requires-Dist: kneed
